[{"code":"001","name":"南关市"},{"code":"002","name":"春阳市"},{"code":"003","name":"二道市"},{"code":"004","name":"绿园市"},{"code":"005","name":"双阳市"},{"code":"006","name":"九台市"},{"code":"007","name":"农安市"},{"code":"008","name":"榆树市"},{"code":"009","name":"德惠市"},{"code":"010","name":"昌邑市"},{"code":"011","name":"龙潭市"},{"code":"012","name":"船营市"},{"code":"013","name":"丰满市"},{"code":"014","name":"永吉市"},{"code":"015","name":"蛟河市"},{"code":"016","name":"桦甸市"},{"code":"017","name":"舒兰市"},{"code":"018","name":"磐石市"},{"code":"019","name":"梨树市"},{"code":"020","name":"伊通市"},{"code":"021","name":"公主岭市"},{"code":"022","name":"双辽市"},{"code":"023","name":"龙山市"},{"code":"024","name":"西安市"},{"code":"025","name":"东丰市"},{"code":"026","name":"东辽市"},{"code":"027","name":"东昌市"},{"code":"028","name":"二道江市"},{"code":"029","name":"通化市"},{"code":"030","name":"辉南市"},{"code":"031","name":"柳河市"},{"code":"032","name":"梅河口市"},{"code":"033","name":"集安市"},{"code":"034","name":"浑江市"},{"code":"035","name":"江源市"},{"code":"036","name":"抚松市"},{"code":"037","name":"靖宇市"},{"code":"038","name":"长白市"},{"code":"039","name":"临江市"},{"code":"040","name":"宁江市"},{"code":"041","name":"前郭尔罗斯市"},{"code":"042","name":"长岭市"},{"code":"043","name":"乾安市"},{"code":"044","name":"扶余市"},{"code":"045","name":"洮北市"},{"code":"046","name":"镇赉市"},{"code":"047","name":"通榆市"},{"code":"048","name":"洮南市"},{"code":"049","name":"大安市"},{"code":"050","name":"延吉市"},{"code":"051","name":"图们市"},{"code":"052","name":"敦化市"},{"code":"053","name":"珲春市"},{"code":"054","name":"龙井市"},{"code":"055","name":"和龙市"},{"code":"056","name":"汪清市"},{"code":"057","name":"安图市"}]